codetest/__init__.py
codetest/_codetest.py
codetest/_utils.py
codetest/codetest.py
codetest/test_codetest.py
codetest-1.1.0.dist-info/LICENSE
codetest-1.1.0.dist-info/METADATA
codetest-1.1.0.dist-info/WHEEL
codetest-1.1.0.dist-info/top_level.txt
codetest-1.1.0.dist-info/RECORD
