Metadata-Version: 2.1
Name: codetest
Version: 1.1.0
Summary: A testing library for coding problems
Home-page: https://github.com/anuragpatil94/codetest
Author: Anurag Patil
Author-email: aspanurag@gmail.com
License: MIT
Keywords: testing,library,Coding
Platform: UNKNOWN
Classifier: Development Status :: 5 - Production/Stable
Classifier: Intended Audience :: Education
Classifier: Operating System :: Microsoft :: Windows :: Windows 10
Classifier: License :: OSI Approved :: MIT License
Classifier: Programming Language :: Python :: 3
Classifier: Programming Language :: Python :: 3.6
Classifier: Programming Language :: Python :: 3.7
Classifier: Programming Language :: Python :: 3.8
